eazyml_genai/__init__.py
eazyml_genai/Linux_x86_64/__init__.py
eazyml_genai/Linux_x86_64/eazyml_genai/__init__.cpython-310-x86_64-linux-gnu.so
eazyml_genai/Linux_x86_64/eazyml_genai/__init__.cpython-311-x86_64-linux-gnu.so
eazyml_genai/Linux_x86_64/eazyml_genai/__init__.cpython-312-x86_64-linux-gnu.so
eazyml_genai/Linux_x86_64/eazyml_genai/__init__.cpython-38-x86_64-linux-gnu.so
eazyml_genai/Linux_x86_64/eazyml_genai/__init__.cpython-39-x86_64-linux-gnu.so
eazyml_genai/Linux_x86_64/eazyml_genai/client.cpython-310-x86_64-linux-gnu.so
eazyml_genai/Linux_x86_64/eazyml_genai/client.cpython-311-x86_64-linux-gnu.so
eazyml_genai/Linux_x86_64/eazyml_genai/client.cpython-312-x86_64-linux-gnu.so
eazyml_genai/Linux_x86_64/eazyml_genai/client.cpython-38-x86_64-linux-gnu.so
eazyml_genai/Linux_x86_64/eazyml_genai/client.cpython-39-x86_64-linux-gnu.so
eazyml_genai/Linux_x86_64/eazyml_genai/components/__init__.cpython-310-x86_64-linux-gnu.so
eazyml_genai/Linux_x86_64/eazyml_genai/components/__init__.cpython-311-x86_64-linux-gnu.so
eazyml_genai/Linux_x86_64/eazyml_genai/components/__init__.cpython-312-x86_64-linux-gnu.so
eazyml_genai/Linux_x86_64/eazyml_genai/components/__init__.cpython-38-x86_64-linux-gnu.so
eazyml_genai/Linux_x86_64/eazyml_genai/components/__init__.cpython-39-x86_64-linux-gnu.so
eazyml_genai/Linux_x86_64/eazyml_genai/components/document_cleaner/document_cleaner.cpython-310-x86_64-linux-gnu.so
eazyml_genai/Linux_x86_64/eazyml_genai/components/document_cleaner/document_cleaner.cpython-311-x86_64-linux-gnu.so
eazyml_genai/Linux_x86_64/eazyml_genai/components/document_cleaner/document_cleaner.cpython-312-x86_64-linux-gnu.so
eazyml_genai/Linux_x86_64/eazyml_genai/components/document_cleaner/document_cleaner.cpython-38-x86_64-linux-gnu.so
eazyml_genai/Linux_x86_64/eazyml_genai/components/document_cleaner/document_cleaner.cpython-39-x86_64-linux-gnu.so
eazyml_genai/Linux_x86_64/eazyml_genai/components/document_cleaner/pdf_cleaner.cpython-310-x86_64-linux-gnu.so
eazyml_genai-0.2.36.dist-info/licenses/LICENSE
eazyml_genai-0.2.36.dist-info/METADATA
eazyml_genai-0.2.36.dist-info/WHEEL
eazyml_genai-0.2.36.dist-info/top_level.txt
eazyml_genai-0.2.36.dist-info/RECORD
